{"frames":{"acc_head_U_gold14_h_lay_he_3569_2_0.png":{"frame":{"x":1,"y":41,"w":20,"h":22},"rotated":true,"trimmed":false,"spriteSourceSize":{"x":0,"y":0,"w":20,"h":22},"sourceSize":{"w":20,"h":22}},"acc_head_U_gold14_h_spk_he_3569_0_0.png":{"frame":{"x":1,"y":1,"w":11,"h":11},"rotated":false,"trimmed":false,"spriteSourceSize":{"x":0,"y":0,"w":11,"h":11},"sourceSize":{"w":11,"h":11}},"acc_head_U_gold14_h_spk_he_3569_1_0.png":{"frame":{"x":14,"y":1,"w":11,"h":19},"rotated":false,"trimmed":false,"spriteSourceSize":{"x":0,"y":0,"w":11,"h":19},"sourceSize":{"w":11,"h":19}},"acc_head_U_gold14_h_spk_he_3569_2_0.png":{"frame":{"x":1,"y":63,"w":24,"h":22},"rotated":false,"trimmed":false,"spriteSourceSize":{"x":0,"y":0,"w":24,"h":22},"sourceSize":{"w":24,"h":22}},"acc_head_U_gold14_h_spk_he_3569_3_0.png":{"frame":{"x":1,"y":22,"w":25,"h":17},"rotated":false,"trimmed":false,"spriteSourceSize":{"x":0,"y":0,"w":25,"h":17},"sourceSize":{"w":25,"h":17}}},"animations":{},"meta":{"app":"https://www.codeandweb.com/texturepacker","version":"1.0","image":"acc_head_U_gold14.png","format":"RGBA4444","size":{"w":27,"h":86},"scale":"1","smartupdate":"$TexturePacker:SmartUpdate:34b10aa4792b966d52c1ffd27f25b41c:640c951a35833dff1cf35b9fa22ba52c:c91d3c4e86069fa2761cee1a0866e1a9$","offset":{"h_lay_he_3569_2_0":[20,49],"h_std_he_3569_0_0":[-40,74],"h_std_he_3569_1_0":[-38,80],"h_std_he_3569_2_0":[-28,81],"h_std_he_3569_3_0":[-22,76],"h_std_he_3569_7_0":[-37,76],"h_spk_he_3569_0_0":[-40,75],"h_spk_he_3569_1_0":[-38,81],"h_spk_he_3569_2_0":[-28,82],"h_spk_he_3569_3_0":[-22,77],"h_spk_he_3569_7_0":[-37,77]}}}