{"manifest":{"name":"bc_gift_14days","version":"0.1","assets":{"index":{},"bc_gift_14days_visualization":{},"bc_gift_14days_assets":{},"bc_gift_14days_logic":{},"bc_gift_14days_64_sd_0_0":{},"bc_gift_14days_64_a_0_0":{},"bc_gift_14days_64_a_2_0":{},"bc_gift_14days_64_b_0_0":{},"bc_gift_14days_64_b_0_1":{},"bc_gift_14days_64_b_0_2":{},"bc_gift_14days_64_b_0_3":{},"bc_gift_14days_64_b_0_4":{},"bc_gift_14days_64_b_0_5":{},"bc_gift_14days_64_c_0_0":{},"bc_gift_14days_64_c_0_1":{},"bc_gift_14days_64_c_0_2":{},"bc_gift_14days_64_c_0_3":{},"bc_gift_14days_64_c_0_4":{},"bc_gift_14days_64_c_0_5":{},"bc_gift_14days_64_d_0_0":{},"bc_gift_14days_64_d_0_1":{},"bc_gift_14days_64_d_0_2":{},"bc_gift_14days_64_d_0_3":{},"bc_gift_14days_64_d_0_4":{},"bc_gift_14days_64_d_0_5":{},"bc_gift_14days_64_e_0_0":{},"bc_gift_14days_64_e_0_1":{},"bc_gift_14days_64_e_0_2":{},"bc_gift_14days_64_e_0_3":{},"bc_gift_14days_64_e_0_4":{},"bc_gift_14days_64_e_0_5":{},"bc_gift_14days_64_e_0_6":{},"bc_gift_14days_64_e_0_7":{},"bc_gift_14days_64_e_0_8":{},"bc_gift_14days_64_e_0_9":{},"bc_gift_14days_64_e_0_10":{},"bc_gift_14days_icon_a":{}},"aliases":{}},"spritesheet":{"frames":{"bc_gift_14days_bc_gift_14days_64_a_0_0.png":{"frame":{"x":372,"y":1,"w":61,"h":67},"rotated":false,"trimmed":false,"spriteSourceSize":{"x":0,"y":0,"w":61,"h":67},"sourceSize":{"w":61,"h":67}},"bc_gift_14days_bc_gift_14days_64_a_2_0.png":{"frame":{"x":372,"y":70,"w":61,"h":67},"rotated":false,"trimmed":false,"spriteSourceSize":{"x":0,"y":0,"w":61,"h":67},"sourceSize":{"w":61,"h":67}},"bc_gift_14days_bc_gift_14days_64_b_0_3.png":{"frame":{"x":14,"y":223,"w":7,"h":7},"rotated":false,"trimmed":false,"spriteSourceSize":{"x":0,"y":0,"w":7,"h":7},"sourceSize":{"w":7,"h":7}},"bc_gift_14days_bc_gift_14days_64_b_0_4.png":{"frame":{"x":1,"y":236,"w":9,"h":9},"rotated":false,"trimmed":false,"spriteSourceSize":{"x":0,"y":0,"w":9,"h":9},"sourceSize":{"w":9,"h":9}},"bc_gift_14days_bc_gift_14days_64_c_0_0.png":{"frame":{"x":191,"y":185,"w":3,"h":3},"rotated":false,"trimmed":false,"spriteSourceSize":{"x":0,"y":0,"w":3,"h":3},"sourceSize":{"w":3,"h":3}},"bc_gift_14days_bc_gift_14days_64_c_0_1.png":{"frame":{"x":32,"y":223,"w":5,"h":5},"rotated":false,"trimmed":false,"spriteSourceSize":{"x":0,"y":0,"w":5,"h":5},"sourceSize":{"w":5,"h":5}},"bc_gift_14days_bc_gift_14days_64_c_0_2.png":{"frame":{"x":23,"y":223,"w":7,"h":7},"rotated":false,"trimmed":false,"spriteSourceSize":{"x":0,"y":0,"w":7,"h":7},"sourceSize":{"w":7,"h":7}},"bc_gift_14days_bc_gift_14days_64_d_0_5.png":{"frame":{"x":1,"y":223,"w":11,"h":11},"rotated":false,"trimmed":false,"spriteSourceSize":{"x":0,"y":0,"w":11,"h":11},"sourceSize":{"w":11,"h":11}},"bc_gift_14days_bc_gift_14days_64_e_0_0.png":{"frame":{"x":362,"y":172,"w":73,"h":73},"rotated":false,"trimmed":false,"spriteSourceSize":{"x":0,"y":0,"w":73,"h":73},"sourceSize":{"w":73,"h":73}},"bc_gift_14days_bc_gift_14days_64_e_0_1.png":{"frame":{"x":281,"y":172,"w":79,"h":79},"rotated":false,"trimmed":false,"spriteSourceSize":{"x":0,"y":0,"w":79,"h":79},"sourceSize":{"w":79,"h":79}},"bc_gift_14days_bc_gift_14days_64_e_0_2.png":{"frame":{"x":285,"y":1,"w":85,"h":85},"rotated":false,"trimmed":false,"spriteSourceSize":{"x":0,"y":0,"w":85,"h":85},"sourceSize":{"w":85,"h":85}},"bc_gift_14days_bc_gift_14days_64_e_0_3.png":{"frame":{"x":1,"y":97,"w":93,"h":93},"rotated":false,"trimmed":false,"spriteSourceSize":{"x":0,"y":0,"w":93,"h":93},"sourceSize":{"w":93,"h":93}},"bc_gift_14days_bc_gift_14days_64_e_0_4.png":{"frame":{"x":96,"y":1,"w":93,"h":93},"rotated":false,"trimmed":false,"spriteSourceSize":{"x":0,"y":0,"w":93,"h":93},"sourceSize":{"w":93,"h":93}},"bc_gift_14days_bc_gift_14days_64_e_0_5.png":{"frame":{"x":96,"y":96,"w":93,"h":93},"rotated":false,"trimmed":false,"spriteSourceSize":{"x":0,"y":0,"w":93,"h":93},"sourceSize":{"w":93,"h":93}},"bc_gift_14days_bc_gift_14days_64_e_0_6.png":{"frame":{"x":1,"y":1,"w":93,"h":94},"rotated":false,"trimmed":false,"spriteSourceSize":{"x":0,"y":0,"w":93,"h":94},"sourceSize":{"w":93,"h":94}},"bc_gift_14days_bc_gift_14days_64_e_0_7.png":{"frame":{"x":191,"y":1,"w":92,"h":92},"rotated":false,"trimmed":false,"spriteSourceSize":{"x":0,"y":0,"w":92,"h":92},"sourceSize":{"w":92,"h":92}},"bc_gift_14days_bc_gift_14days_64_e_0_8.png":{"frame":{"x":191,"y":95,"w":88,"h":88},"rotated":false,"trimmed":false,"spriteSourceSize":{"x":0,"y":0,"w":88,"h":88},"sourceSize":{"w":88,"h":88}},"bc_gift_14days_bc_gift_14days_64_e_0_9.png":{"frame":{"x":285,"y":88,"w":82,"h":84},"rotated":true,"trimmed":false,"spriteSourceSize":{"x":0,"y":0,"w":82,"h":84},"sourceSize":{"w":82,"h":84}},"bc_gift_14days_bc_gift_14days_64_e_0_10.png":{"frame":{"x":281,"y":95,"w":1,"h":1},"rotated":false,"trimmed":false,"spriteSourceSize":{"x":0,"y":0,"w":1,"h":1},"sourceSize":{"w":1,"h":1}},"bc_gift_14days_bc_gift_14days_64_sd_0_0.png":{"frame":{"x":1,"y":192,"w":57,"h":29},"rotated":false,"trimmed":false,"spriteSourceSize":{"x":0,"y":0,"w":57,"h":29},"sourceSize":{"w":57,"h":29}},"bc_gift_14days_bc_gift_14days_icon_a.png":{"frame":{"x":60,"y":192,"w":29,"h":30},"rotated":true,"trimmed":false,"spriteSourceSize":{"x":0,"y":0,"w":29,"h":30},"sourceSize":{"w":29,"h":30}}},"animations":{"bc_gift_14days_bc_gift_14days_64_b_0":["bc_gift_14days_bc_gift_14days_64_b_0_3.png","bc_gift_14days_bc_gift_14days_64_b_0_4.png"],"bc_gift_14days_bc_gift_14days_64_c_0":["bc_gift_14days_bc_gift_14days_64_c_0_0.png","bc_gift_14days_bc_gift_14days_64_c_0_1.png","bc_gift_14days_bc_gift_14days_64_c_0_2.png"],"bc_gift_14days_bc_gift_14days_64_e_0":["bc_gift_14days_bc_gift_14days_64_e_0_0.png","bc_gift_14days_bc_gift_14days_64_e_0_1.png","bc_gift_14days_bc_gift_14days_64_e_0_2.png","bc_gift_14days_bc_gift_14days_64_e_0_3.png","bc_gift_14days_bc_gift_14days_64_e_0_4.png","bc_gift_14days_bc_gift_14days_64_e_0_5.png","bc_gift_14days_bc_gift_14days_64_e_0_6.png","bc_gift_14days_bc_gift_14days_64_e_0_7.png","bc_gift_14days_bc_gift_14days_64_e_0_8.png","bc_gift_14days_bc_gift_14days_64_e_0_9.png","bc_gift_14days_bc_gift_14days_64_e_0_10.png"]},"meta":{"app":"https://www.codeandweb.com/texturepacker","version":"1.0","image":"bc_gift_14days.png","format":"RGBA8888","size":{"w":436,"h":252},"scale":"1","smartupdate":"$TexturePacker:SmartUpdate:5af88695ec7cb6805a1768f78fc9d154:a584c388150608ab0f86844c826e0547:ddae4a3672165ff0b303fdd0826cd68b$"}},"animations":{}}