{"manifest":{"name":"uni_projector","version":"0.1","assets":{"index":{},"uni_projector_visualization":{},"uni_projector_assets":{},"uni_projector_logic":{},"uni_projector_64_sd_4_0":{},"uni_projector_64_a_4_0":{},"uni_projector_64_b_4_0":{},"uni_projector_64_c_4_0":{},"uni_projector_64_d_4_0":{},"uni_projector_64_e_4_0":{},"uni_projector_64_f_4_0":{},"uni_projector_sd_2_0":{},"uni_projector_64_a_2_0":{},"uni_projector_64_b_2_0":{},"uni_projector_64_c_2_0":{},"uni_projector_64_d_2_0":{},"uni_projector_64_e_2_0":{},"uni_projector_64_f_2_0":{},"uni_projector_32_sd_4_0":{},"uni_projector_32_a_4_0":{},"uni_projector_32_b_4_0":{},"uni_projector_32_c_4_0":{},"uni_projector_32_d_4_0":{},"uni_projector_32_e_4_0":{},"uni_projector_32_f_4_0":{},"uni_projector_32_sd_2_0":{},"uni_projector_32_a_2_0":{},"uni_projector_32_b_2_0":{},"uni_projector_32_c_2_0":{},"uni_projector_32_d_2_0":{},"uni_projector_32_e_2_0":{},"uni_projector_32_f_2_0":{},"uni_projector_icon_a":{},"uni_projector_64_sd_2_0":{}},"aliases":{}},"spritesheet":{"frames":{"uni_projector_uni_projector_32_a_2_0.png":{"frame":{"x":30,"y":680,"w":18,"h":70},"rotated":false,"trimmed":false,"spriteSourceSize":{"x":0,"y":0,"w":18,"h":70},"sourceSize":{"w":18,"h":70}},"uni_projector_uni_projector_32_a_4_0.png":{"frame":{"x":50,"y":680,"w":18,"h":70},"rotated":false,"trimmed":false,"spriteSourceSize":{"x":0,"y":0,"w":18,"h":70},"sourceSize":{"w":18,"h":70}},"uni_projector_uni_projector_32_b_2_0.png":{"frame":{"x":70,"y":680,"w":16,"h":68},"rotated":false,"trimmed":false,"spriteSourceSize":{"x":0,"y":0,"w":16,"h":68},"sourceSize":{"w":16,"h":68}},"uni_projector_uni_projector_32_b_4_0.png":{"frame":{"x":88,"y":628,"w":16,"h":68},"rotated":false,"trimmed":false,"spriteSourceSize":{"x":0,"y":0,"w":16,"h":68},"sourceSize":{"w":16,"h":68}},"uni_projector_uni_projector_32_c_2_0.png":{"frame":{"x":88,"y":698,"w":16,"h":54},"rotated":false,"trimmed":false,"spriteSourceSize":{"x":0,"y":0,"w":16,"h":54},"sourceSize":{"w":16,"h":54}},"uni_projector_uni_projector_32_c_4_0.png":{"frame":{"x":108,"y":722,"w":16,"h":54},"rotated":false,"trimmed":false,"spriteSourceSize":{"x":0,"y":0,"w":16,"h":54},"sourceSize":{"w":16,"h":54}},"uni_projector_uni_projector_32_d_2_0.png":{"frame":{"x":40,"y":752,"w":32,"h":37},"rotated":false,"trimmed":false,"spriteSourceSize":{"x":0,"y":0,"w":32,"h":37},"sourceSize":{"w":32,"h":37}},"uni_projector_uni_projector_32_d_4_0.png":{"frame":{"x":1,"y":760,"w":23,"h":37},"rotated":true,"trimmed":false,"spriteSourceSize":{"x":0,"y":0,"w":23,"h":37},"sourceSize":{"w":23,"h":37}},"uni_projector_uni_projector_32_e_2_0.png":{"frame":{"x":81,"y":575,"w":41,"h":51},"rotated":false,"trimmed":false,"spriteSourceSize":{"x":0,"y":0,"w":41,"h":51},"sourceSize":{"w":41,"h":51}},"uni_projector_uni_projector_32_e_4_0.png":{"frame":{"x":35,"y":637,"w":41,"h":51},"rotated":true,"trimmed":false,"spriteSourceSize":{"x":0,"y":0,"w":41,"h":51},"sourceSize":{"w":41,"h":51}},"uni_projector_uni_projector_32_f_2_0.png":{"frame":{"x":81,"y":487,"w":42,"h":45},"rotated":true,"trimmed":false,"spriteSourceSize":{"x":0,"y":0,"w":42,"h":45},"sourceSize":{"w":42,"h":45}},"uni_projector_uni_projector_32_f_4_0.png":{"frame":{"x":81,"y":531,"w":42,"h":45},"rotated":true,"trimmed":false,"spriteSourceSize":{"x":0,"y":0,"w":42,"h":45},"sourceSize":{"w":42,"h":45}},"uni_projector_uni_projector_32_sd_2_0.png":{"frame":{"x":106,"y":628,"w":45,"h":20},"rotated":true,"trimmed":false,"spriteSourceSize":{"x":0,"y":0,"w":45,"h":20},"sourceSize":{"w":45,"h":20}},"uni_projector_uni_projector_32_sd_4_0.png":{"frame":{"x":106,"y":675,"w":45,"h":20},"rotated":true,"trimmed":false,"spriteSourceSize":{"x":0,"y":0,"w":45,"h":20},"sourceSize":{"w":45,"h":20}},"uni_projector_uni_projector_64_a_2_0.png":{"frame":{"x":87,"y":1,"w":39,"h":137},"rotated":false,"trimmed":false,"spriteSourceSize":{"x":0,"y":0,"w":39,"h":137},"sourceSize":{"w":39,"h":137}},"uni_projector_uni_projector_64_a_4_0.png":{"frame":{"x":87,"y":140,"w":39,"h":137},"rotated":false,"trimmed":false,"spriteSourceSize":{"x":0,"y":0,"w":39,"h":137},"sourceSize":{"w":39,"h":137}},"uni_projector_uni_projector_64_b_2_0.png":{"frame":{"x":1,"y":401,"w":32,"h":133},"rotated":false,"trimmed":false,"spriteSourceSize":{"x":0,"y":0,"w":32,"h":133},"sourceSize":{"w":32,"h":133}},"uni_projector_uni_projector_64_b_4_0.png":{"frame":{"x":1,"y":536,"w":32,"h":133},"rotated":false,"trimmed":false,"spriteSourceSize":{"x":0,"y":0,"w":32,"h":133},"sourceSize":{"w":32,"h":133}},"uni_projector_uni_projector_64_c_2_0.png":{"frame":{"x":1,"y":671,"w":27,"h":87},"rotated":false,"trimmed":false,"spriteSourceSize":{"x":0,"y":0,"w":27,"h":87},"sourceSize":{"w":27,"h":87}},"uni_projector_uni_projector_64_c_4_0.png":{"frame":{"x":87,"y":279,"w":27,"h":87},"rotated":false,"trimmed":false,"spriteSourceSize":{"x":0,"y":0,"w":27,"h":87},"sourceSize":{"w":27,"h":87}},"uni_projector_uni_projector_64_d_2_0.png":{"frame":{"x":35,"y":487,"w":44,"h":73},"rotated":false,"trimmed":false,"spriteSourceSize":{"x":0,"y":0,"w":44,"h":73},"sourceSize":{"w":44,"h":73}},"uni_projector_uni_projector_64_d_4_0.png":{"frame":{"x":35,"y":562,"w":44,"h":73},"rotated":false,"trimmed":false,"spriteSourceSize":{"x":0,"y":0,"w":44,"h":73},"sourceSize":{"w":44,"h":73}},"uni_projector_uni_projector_64_e_2_0.png":{"frame":{"x":1,"y":1,"w":84,"h":105},"rotated":false,"trimmed":false,"spriteSourceSize":{"x":0,"y":0,"w":84,"h":105},"sourceSize":{"w":84,"h":105}},"uni_projector_uni_projector_64_e_4_0.png":{"frame":{"x":1,"y":108,"w":84,"h":105},"rotated":false,"trimmed":false,"spriteSourceSize":{"x":0,"y":0,"w":84,"h":105},"sourceSize":{"w":84,"h":105}},"uni_projector_uni_projector_64_f_2_0.png":{"frame":{"x":1,"y":215,"w":84,"h":91},"rotated":false,"trimmed":false,"spriteSourceSize":{"x":0,"y":0,"w":84,"h":91},"sourceSize":{"w":84,"h":91}},"uni_projector_uni_projector_64_f_4_0.png":{"frame":{"x":1,"y":308,"w":84,"h":91},"rotated":false,"trimmed":false,"spriteSourceSize":{"x":0,"y":0,"w":84,"h":91},"sourceSize":{"w":84,"h":91}},"uni_projector_uni_projector_64_sd_2_0.png":{"frame":{"x":35,"y":401,"w":91,"h":41},"rotated":false,"trimmed":false,"spriteSourceSize":{"x":0,"y":0,"w":91,"h":41},"sourceSize":{"w":91,"h":41}},"uni_projector_uni_projector_64_sd_4_0.png":{"frame":{"x":35,"y":444,"w":91,"h":41},"rotated":false,"trimmed":false,"spriteSourceSize":{"x":0,"y":0,"w":91,"h":41},"sourceSize":{"w":91,"h":41}},"uni_projector_uni_projector_icon_a.png":{"frame":{"x":74,"y":754,"w":32,"h":32},"rotated":false,"trimmed":false,"spriteSourceSize":{"x":0,"y":0,"w":32,"h":32},"sourceSize":{"w":32,"h":32}}},"animations":{},"meta":{"app":"https://www.codeandweb.com/texturepacker","version":"1.0","image":"uni_projector.png","format":"RGBA8888","size":{"w":127,"h":790},"scale":"1","smartupdate":"$TexturePacker:SmartUpdate:1af89c2f77884c619352ba47b6ffd850:8b0524cd9bdf2e351e99403951b09f14:df609e3129145ab6cfb69fe2bc9603e9$"}},"animations":{}}