{"manifest":{"name":"horse_hairstyle_5","version":"0.1","assets":{"index":{},"horse_hairstyle_5_visualization":{},"horse_hairstyle_5_assets":{},"horse_hairstyle_5_logic":{},"horse_hairstyle_5_64_a_2_0":{},"horse_hairstyle_5_32_a_2_0":{},"horse_hairstyle_5_icon_a":{}},"aliases":{}},"spritesheet":{"frames":{"horse_hairstyle_5_horse_hairstyle_5_32_a_2_0.png":{"frame":{"x":1,"y":1,"w":24,"h":50},"rotated":true,"trimmed":false,"spriteSourceSize":{"x":0,"y":0,"w":24,"h":50},"sourceSize":{"w":24,"h":50}},"horse_hairstyle_5_horse_hairstyle_5_64_a_2_0.png":{"frame":{"x":1,"y":28,"w":47,"h":100},"rotated":true,"trimmed":false,"spriteSourceSize":{"x":0,"y":0,"w":47,"h":100},"sourceSize":{"w":47,"h":100}},"horse_hairstyle_5_horse_hairstyle_5_icon_a.png":{"frame":{"x":53,"y":1,"w":25,"h":32},"rotated":true,"trimmed":false,"spriteSourceSize":{"x":0,"y":0,"w":25,"h":32},"sourceSize":{"w":25,"h":32}}},"animations":{},"meta":{"app":"https://www.codeandweb.com/texturepacker","version":"1.0","image":"horse_hairstyle_5.png","format":"RGBA8888","size":{"w":102,"h":76},"scale":"1","smartupdate":"$TexturePacker:SmartUpdate:e104895b2506a7b55e80dbd296255254:02b07205dc5f7fffbbba79928fea7a43:1cda3904bc6022c7c79fe34d65651684$"}},"animations":{}}