{"manifest":{"name":"eleblock9","version":"0.1","assets":{"index":{},"eleblock9_visualization":{},"eleblock9_assets":{},"eleblock9_logic":{},"eleblock9_64_a_0_1":{},"eleblock9_64_a_0_2":{},"eleblock9_64_a_0_3":{},"eleblock9_64_a_0_4":{},"eleblock9_64_a_0_0":{},"eleblock9_icon_a":{},"eleblock9_32_a_0_0":{},"eleblock9_32_a_0_1":{},"eleblock9_32_a_0_2":{},"eleblock9_32_a_0_3":{},"eleblock9_32_a_0_4":{}},"aliases":{}},"spritesheet":{"frames":{"eleblock9_eleblock9_32_a_0_0.png":{"frame":{"x":57,"y":205,"w":31,"h":17},"rotated":false,"trimmed":false,"spriteSourceSize":{"x":0,"y":0,"w":31,"h":17},"sourceSize":{"w":31,"h":17}},"eleblock9_eleblock9_32_a_0_1.png":{"frame":{"x":24,"y":205,"w":31,"h":24},"rotated":false,"trimmed":false,"spriteSourceSize":{"x":0,"y":0,"w":31,"h":24},"sourceSize":{"w":31,"h":24}},"eleblock9_eleblock9_32_a_0_2.png":{"frame":{"x":68,"y":170,"w":31,"h":33},"rotated":false,"trimmed":false,"spriteSourceSize":{"x":0,"y":0,"w":31,"h":33},"sourceSize":{"w":31,"h":33}},"eleblock9_eleblock9_32_a_0_3.png":{"frame":{"x":90,"y":137,"w":31,"h":40},"rotated":true,"trimmed":false,"spriteSourceSize":{"x":0,"y":0,"w":31,"h":40},"sourceSize":{"w":31,"h":40}},"eleblock9_eleblock9_32_a_0_4.png":{"frame":{"x":101,"y":170,"w":31,"h":48},"rotated":false,"trimmed":false,"spriteSourceSize":{"x":0,"y":0,"w":31,"h":48},"sourceSize":{"w":31,"h":48}},"eleblock9_eleblock9_64_a_0_0.png":{"frame":{"x":100,"y":1,"w":66,"h":33},"rotated":true,"trimmed":false,"spriteSourceSize":{"x":0,"y":0,"w":66,"h":33},"sourceSize":{"w":66,"h":33}},"eleblock9_eleblock9_64_a_0_1.png":{"frame":{"x":84,"y":69,"w":66,"h":49},"rotated":true,"trimmed":false,"spriteSourceSize":{"x":0,"y":0,"w":66,"h":49},"sourceSize":{"w":66,"h":49}},"eleblock9_eleblock9_64_a_0_2.png":{"frame":{"x":1,"y":137,"w":66,"h":65},"rotated":true,"trimmed":false,"spriteSourceSize":{"x":0,"y":0,"w":66,"h":65},"sourceSize":{"w":66,"h":65}},"eleblock9_eleblock9_64_a_0_3.png":{"frame":{"x":1,"y":69,"w":66,"h":81},"rotated":true,"trimmed":false,"spriteSourceSize":{"x":0,"y":0,"w":66,"h":81},"sourceSize":{"w":66,"h":81}},"eleblock9_eleblock9_64_a_0_4.png":{"frame":{"x":1,"y":1,"w":66,"h":97},"rotated":true,"trimmed":false,"spriteSourceSize":{"x":0,"y":0,"w":66,"h":97},"sourceSize":{"w":66,"h":97}},"eleblock9_eleblock9_icon_a.png":{"frame":{"x":1,"y":205,"w":28,"h":21},"rotated":true,"trimmed":false,"spriteSourceSize":{"x":0,"y":0,"w":28,"h":21},"sourceSize":{"w":28,"h":21}}},"animations":{"eleblock9_eleblock9_32_a_0":["eleblock9_eleblock9_32_a_0_0.png","eleblock9_eleblock9_32_a_0_1.png","eleblock9_eleblock9_32_a_0_2.png","eleblock9_eleblock9_32_a_0_3.png","eleblock9_eleblock9_32_a_0_4.png"],"eleblock9_eleblock9_64_a_0":["eleblock9_eleblock9_64_a_0_0.png","eleblock9_eleblock9_64_a_0_1.png","eleblock9_eleblock9_64_a_0_2.png","eleblock9_eleblock9_64_a_0_3.png","eleblock9_eleblock9_64_a_0_4.png"]},"meta":{"app":"https://www.codeandweb.com/texturepacker","version":"1.0","image":"eleblock9.png","format":"RGBA8888","size":{"w":134,"h":234},"scale":"1","smartupdate":"$TexturePacker:SmartUpdate:6da08997864744f2f34b36fd185c4046:3f2a64273f2aa33ef88033c987649f95:8f01fd3da7da5d7eda068ea003c043ed$"}},"animations":{}}