{"manifest":{"name":"room_noob_stairside","version":"0.1","assets":{"index":{},"room_noob_stairside_visualization":{},"room_noob_stairside_assets":{},"room_noob_stairside_logic":{},"room_noob_stairside_64_a_2_0":{},"room_noob_stairside_64_b_2_0":{},"room_noob_stairside_64_a_0_0":{},"room_noob_stairside_64_b_0_0":{},"room_noob_stairside_32_a_2_0":{},"room_noob_stairside_32_b_2_0":{},"room_noob_stairside_32_a_0_0":{},"room_noob_stairside_32_b_0_0":{},"room_noob_stairside_icon_a":{}},"aliases":{}},"spritesheet":{"frames":{"room_noob_stairside_room_noob_stairside_32_a_0_0.png":{"frame":{"x":197,"y":159,"w":32,"h":48},"rotated":false,"trimmed":false,"spriteSourceSize":{"x":0,"y":0,"w":32,"h":48},"sourceSize":{"w":32,"h":48}},"room_noob_stairside_room_noob_stairside_32_a_2_0.png":{"frame":{"x":197,"y":109,"w":34,"h":48},"rotated":false,"trimmed":false,"spriteSourceSize":{"x":0,"y":0,"w":34,"h":48},"sourceSize":{"w":34,"h":48}},"room_noob_stairside_room_noob_stairside_32_b_0_0.png":{"frame":{"x":132,"y":174,"w":42,"h":53},"rotated":true,"trimmed":false,"spriteSourceSize":{"x":0,"y":0,"w":42,"h":53},"sourceSize":{"w":42,"h":53}},"room_noob_stairside_room_noob_stairside_32_b_2_0.png":{"frame":{"x":132,"y":109,"w":63,"h":63},"rotated":false,"trimmed":false,"spriteSourceSize":{"x":0,"y":0,"w":63,"h":63},"sourceSize":{"w":63,"h":63}},"room_noob_stairside_room_noob_stairside_64_a_0_0.png":{"frame":{"x":67,"y":129,"w":63,"h":97},"rotated":false,"trimmed":false,"spriteSourceSize":{"x":0,"y":0,"w":63,"h":97},"sourceSize":{"w":63,"h":97}},"room_noob_stairside_room_noob_stairside_64_a_2_0.png":{"frame":{"x":1,"y":129,"w":64,"h":97},"rotated":false,"trimmed":false,"spriteSourceSize":{"x":0,"y":0,"w":64,"h":97},"sourceSize":{"w":64,"h":97}},"room_noob_stairside_room_noob_stairside_64_b_0_0.png":{"frame":{"x":129,"y":1,"w":80,"h":106},"rotated":false,"trimmed":false,"spriteSourceSize":{"x":0,"y":0,"w":80,"h":106},"sourceSize":{"w":80,"h":106}},"room_noob_stairside_room_noob_stairside_64_b_2_0.png":{"frame":{"x":1,"y":1,"w":126,"h":126},"rotated":false,"trimmed":false,"spriteSourceSize":{"x":0,"y":0,"w":126,"h":126},"sourceSize":{"w":126,"h":126}},"room_noob_stairside_room_noob_stairside_icon_a.png":{"frame":{"x":211,"y":1,"w":20,"h":29},"rotated":false,"trimmed":false,"spriteSourceSize":{"x":0,"y":0,"w":20,"h":29},"sourceSize":{"w":20,"h":29}}},"animations":{},"meta":{"app":"https://www.codeandweb.com/texturepacker","version":"1.0","image":"room_noob_stairside.png","format":"RGBA8888","size":{"w":232,"h":227},"scale":"1","smartupdate":"$TexturePacker:SmartUpdate:65a00f74372850d9e7a3c4668401af55:a6d34e7eabeba29aa67706e4b2a8860f:4dfc0813be3e6abdf0591a26a0211b3f$"}},"animations":{}}