{"manifest":{"version":"0.1","assets":{"h_std_fx166_1_1_0_0":{"offset":"2,80"},"h_std_fx166_1_1_1_0":{"offset":"-6,81"},"h_std_fx166_1_1_2_0":{"offset":"3,80"},"h_std_fx166_1_1_3_0":{"offset":"-3,80"},"h_std_fx166_1_1_4_0":{"offset":"-10,80"},"h_std_fx166_1_1_5_0":{"offset":"-7,81"},"h_std_fx166_1_1_6_0":{"offset":"-14,80"},"h_std_fx166_1_1_7_0":{"offset":"-6,79"}},"aliases":{}},"spritesheet":{"frames":{"Goblin_h_std_fx166_1_1_0_0.png":{"frame":{"x":58,"y":1,"w":52,"h":41},"rotated":false,"trimmed":false,"spriteSourceSize":{"x":0,"y":0,"w":52,"h":41},"sourceSize":{"w":52,"h":41}},"Goblin_h_std_fx166_1_1_1_0.png":{"frame":{"x":55,"y":44,"w":51,"h":47},"rotated":false,"trimmed":false,"spriteSourceSize":{"x":0,"y":0,"w":51,"h":47},"sourceSize":{"w":51,"h":47}},"Goblin_h_std_fx166_1_1_2_0.png":{"frame":{"x":54,"y":93,"w":57,"h":48},"rotated":false,"trimmed":false,"spriteSourceSize":{"x":0,"y":0,"w":57,"h":48},"sourceSize":{"w":57,"h":48}},"Goblin_h_std_fx166_1_1_3_0.png":{"frame":{"x":51,"y":143,"w":61,"h":49},"rotated":false,"trimmed":false,"spriteSourceSize":{"x":0,"y":0,"w":61,"h":49},"sourceSize":{"w":61,"h":49}},"Goblin_h_std_fx166_1_1_4_0.png":{"frame":{"x":1,"y":133,"w":57,"h":48},"rotated":true,"trimmed":false,"spriteSourceSize":{"x":0,"y":0,"w":57,"h":48},"sourceSize":{"w":57,"h":48}},"Goblin_h_std_fx166_1_1_5_0.png":{"frame":{"x":1,"y":84,"w":51,"h":47},"rotated":false,"trimmed":false,"spriteSourceSize":{"x":0,"y":0,"w":51,"h":47},"sourceSize":{"w":51,"h":47}},"Goblin_h_std_fx166_1_1_6_0.png":{"frame":{"x":1,"y":41,"w":52,"h":41},"rotated":false,"trimmed":false,"spriteSourceSize":{"x":0,"y":0,"w":52,"h":41},"sourceSize":{"w":52,"h":41}},"Goblin_h_std_fx166_1_1_7_0.png":{"frame":{"x":1,"y":1,"w":55,"h":38},"rotated":false,"trimmed":false,"spriteSourceSize":{"x":0,"y":0,"w":55,"h":38},"sourceSize":{"w":55,"h":38}}},"animations":{},"meta":{"app":"https://www.codeandweb.com/texturepacker","version":"1.0","image":"Goblin.png","format":"RGBA8888","size":{"w":113,"h":193},"scale":"1","smartupdate":"$TexturePacker:SmartUpdate:141b8ebd47db43f43dbee981258c5d19:2870801387e04e4aadfa7040ff32243e:86147a9479046d4f78da5da03d0f7faf$"}},"animations":{"fx.166":{"desc":"Goblin","remove":["ha","he","hr","hrb","hd"],"sprites":{"fx166_1":{"member":"std_fx166_1_1","directions":{"0":{"dz":2},"1":{"dz":2},"2":{"dz":2},"3":{"dz":2},"4":{"dz":2},"5":{"dz":2},"6":{"dz":2},"7":{"dz":2}}}}}}}