{"manifest":{"name":"hween_c15_evilcloud","version":"0.1","assets":{"index":{},"hween_c15_evilcloud_visualization":{},"hween_c15_evilcloud_assets":{},"hween_c15_evilcloud_logic":{},"hween_c15_evilcloud_64_a_0_0":{},"hween_c15_evilcloud_64_a_0_1":{},"hween_c15_evilcloud_64_a_0_2":{},"hween_c15_evilcloud_64_a_0_3":{},"hween_c15_evilcloud_64_a_0_4":{},"hween_c15_evilcloud_64_a_0_5":{},"hween_c15_evilcloud_64_a_0_6":{},"hween_c15_evilcloud_64_a_0_7":{},"hween_c15_evilcloud_64_b_0_0":{},"hween_c15_evilcloud_64_c_0_0":{},"hween_c15_evilcloud_64_c_0_1":{},"hween_c15_evilcloud_64_c_0_2":{},"hween_c15_evilcloud_64_c_0_3":{},"hween_c15_evilcloud_64_c_0_4":{},"hween_c15_evilcloud_64_c_0_5":{},"hween_c15_evilcloud_64_c_0_6":{},"hween_c15_evilcloud_64_d_0_0":{},"hween_c15_evilcloud_64_d_0_1":{},"hween_c15_evilcloud_64_d_0_2":{},"hween_c15_evilcloud_64_d_0_3":{},"hween_c15_evilcloud_icon_a":{}},"aliases":{}},"spritesheet":{"frames":{"hween_c15_evilcloud_hween_c15_evilcloud_64_a_0_0.png":{"frame":{"x":1,"y":1,"w":105,"h":272},"rotated":false,"trimmed":false,"spriteSourceSize":{"x":0,"y":0,"w":105,"h":272},"sourceSize":{"w":105,"h":272}},"hween_c15_evilcloud_hween_c15_evilcloud_64_a_0_1.png":{"frame":{"x":108,"y":1,"w":100,"h":272},"rotated":false,"trimmed":false,"spriteSourceSize":{"x":0,"y":0,"w":100,"h":272},"sourceSize":{"w":100,"h":272}},"hween_c15_evilcloud_hween_c15_evilcloud_64_a_0_2.png":{"frame":{"x":156,"y":288,"w":96,"h":272},"rotated":true,"trimmed":false,"spriteSourceSize":{"x":0,"y":0,"w":96,"h":272},"sourceSize":{"w":96,"h":272}},"hween_c15_evilcloud_hween_c15_evilcloud_64_a_0_3.png":{"frame":{"x":210,"y":1,"w":95,"h":271},"rotated":true,"trimmed":false,"spriteSourceSize":{"x":0,"y":0,"w":95,"h":271},"sourceSize":{"w":95,"h":271}},"hween_c15_evilcloud_hween_c15_evilcloud_64_a_0_4.png":{"frame":{"x":210,"y":98,"w":94,"h":271},"rotated":true,"trimmed":false,"spriteSourceSize":{"x":0,"y":0,"w":94,"h":271},"sourceSize":{"w":94,"h":271}},"hween_c15_evilcloud_hween_c15_evilcloud_64_a_0_5.png":{"frame":{"x":210,"y":194,"w":92,"h":269},"rotated":true,"trimmed":false,"spriteSourceSize":{"x":0,"y":0,"w":92,"h":269},"sourceSize":{"w":92,"h":269}},"hween_c15_evilcloud_hween_c15_evilcloud_64_a_0_6.png":{"frame":{"x":156,"y":386,"w":88,"h":267},"rotated":true,"trimmed":false,"spriteSourceSize":{"x":0,"y":0,"w":88,"h":267},"sourceSize":{"w":88,"h":267}},"hween_c15_evilcloud_hween_c15_evilcloud_64_b_0_0.png":{"frame":{"x":1,"y":275,"w":153,"h":111},"rotated":false,"trimmed":false,"spriteSourceSize":{"x":0,"y":0,"w":153,"h":111},"sourceSize":{"w":153,"h":111}},"hween_c15_evilcloud_hween_c15_evilcloud_64_c_0_1.png":{"frame":{"x":1,"y":388,"w":73,"h":40},"rotated":false,"trimmed":false,"spriteSourceSize":{"x":0,"y":0,"w":73,"h":40},"sourceSize":{"w":73,"h":40}},"hween_c15_evilcloud_hween_c15_evilcloud_64_c_0_2.png":{"frame":{"x":1,"y":430,"w":73,"h":40},"rotated":false,"trimmed":false,"spriteSourceSize":{"x":0,"y":0,"w":73,"h":40},"sourceSize":{"w":73,"h":40}},"hween_c15_evilcloud_hween_c15_evilcloud_64_c_0_3.png":{"frame":{"x":76,"y":388,"w":73,"h":40},"rotated":false,"trimmed":false,"spriteSourceSize":{"x":0,"y":0,"w":73,"h":40},"sourceSize":{"w":73,"h":40}},"hween_c15_evilcloud_hween_c15_evilcloud_64_c_0_4.png":{"frame":{"x":76,"y":430,"w":73,"h":40},"rotated":false,"trimmed":false,"spriteSourceSize":{"x":0,"y":0,"w":73,"h":40},"sourceSize":{"w":73,"h":40}},"hween_c15_evilcloud_hween_c15_evilcloud_64_c_0_5.png":{"frame":{"x":425,"y":386,"w":72,"h":39},"rotated":true,"trimmed":false,"spriteSourceSize":{"x":0,"y":0,"w":72,"h":39},"sourceSize":{"w":72,"h":39}},"hween_c15_evilcloud_hween_c15_evilcloud_64_c_0_6.png":{"frame":{"x":480,"y":288,"w":1,"h":1},"rotated":false,"trimmed":false,"spriteSourceSize":{"x":0,"y":0,"w":1,"h":1},"sourceSize":{"w":1,"h":1}},"hween_c15_evilcloud_hween_c15_evilcloud_64_d_0_0.png":{"frame":{"x":430,"y":288,"w":48,"h":75},"rotated":false,"trimmed":false,"spriteSourceSize":{"x":0,"y":0,"w":48,"h":75},"sourceSize":{"w":48,"h":75}},"hween_c15_evilcloud_hween_c15_evilcloud_icon_a.png":{"frame":{"x":425,"y":460,"w":30,"h":30},"rotated":false,"trimmed":false,"spriteSourceSize":{"x":0,"y":0,"w":30,"h":30},"sourceSize":{"w":30,"h":30}}},"animations":{"hween_c15_evilcloud_hween_c15_evilcloud_64_a_0":["hween_c15_evilcloud_hween_c15_evilcloud_64_a_0_0.png","hween_c15_evilcloud_hween_c15_evilcloud_64_a_0_1.png","hween_c15_evilcloud_hween_c15_evilcloud_64_a_0_2.png","hween_c15_evilcloud_hween_c15_evilcloud_64_a_0_3.png","hween_c15_evilcloud_hween_c15_evilcloud_64_a_0_4.png","hween_c15_evilcloud_hween_c15_evilcloud_64_a_0_5.png","hween_c15_evilcloud_hween_c15_evilcloud_64_a_0_6.png"],"hween_c15_evilcloud_hween_c15_evilcloud_64_c_0":["hween_c15_evilcloud_hween_c15_evilcloud_64_c_0_1.png","hween_c15_evilcloud_hween_c15_evilcloud_64_c_0_2.png","hween_c15_evilcloud_hween_c15_evilcloud_64_c_0_3.png","hween_c15_evilcloud_hween_c15_evilcloud_64_c_0_4.png","hween_c15_evilcloud_hween_c15_evilcloud_64_c_0_5.png","hween_c15_evilcloud_hween_c15_evilcloud_64_c_0_6.png"]},"meta":{"app":"https://www.codeandweb.com/texturepacker","version":"1.0","image":"hween_c15_evilcloud.png","format":"RGBA8888","size":{"w":482,"h":491},"scale":"1","smartupdate":"$TexturePacker:SmartUpdate:0c3768d62c1116c21d6ba47c16aee5eb:20f713820c28b9ff2a44d796345ab771:c4edf78a250d3505838cea7f5ac2990e$"}},"animations":{}}