{"frames":{"hat_U_sparkleparty2_h_lsp_ha_3300_2_0.png":{"frame":{"x":1,"y":1,"w":21,"h":20},"rotated":false,"trimmed":false,"spriteSourceSize":{"x":0,"y":0,"w":21,"h":20},"sourceSize":{"w":21,"h":20}},"hat_U_sparkleparty2_h_spk_ha_3300_0_0.png":{"frame":{"x":1,"y":23,"w":21,"h":18},"rotated":false,"trimmed":false,"spriteSourceSize":{"x":0,"y":0,"w":21,"h":18},"sourceSize":{"w":21,"h":18}},"hat_U_sparkleparty2_h_spk_ha_3300_1_0.png":{"frame":{"x":1,"y":83,"w":21,"h":16},"rotated":false,"trimmed":false,"spriteSourceSize":{"x":0,"y":0,"w":21,"h":16},"sourceSize":{"w":21,"h":16}},"hat_U_sparkleparty2_h_spk_ha_3300_2_0.png":{"frame":{"x":1,"y":43,"w":21,"h":18},"rotated":false,"trimmed":false,"spriteSourceSize":{"x":0,"y":0,"w":21,"h":18},"sourceSize":{"w":21,"h":18}},"hat_U_sparkleparty2_h_spk_ha_3300_7_0.png":{"frame":{"x":1,"y":101,"w":21,"h":16},"rotated":false,"trimmed":false,"spriteSourceSize":{"x":0,"y":0,"w":21,"h":16},"sourceSize":{"w":21,"h":16}},"hat_U_sparkleparty2_h_std_ha_3300_1_0.png":{"frame":{"x":1,"y":119,"w":21,"h":16},"rotated":false,"trimmed":false,"spriteSourceSize":{"x":0,"y":0,"w":21,"h":16},"sourceSize":{"w":21,"h":16}},"hat_U_sparkleparty2_h_std_ha_3300_2_0.png":{"frame":{"x":1,"y":63,"w":21,"h":18},"rotated":false,"trimmed":false,"spriteSourceSize":{"x":0,"y":0,"w":21,"h":18},"sourceSize":{"w":21,"h":18}},"hat_U_sparkleparty2_h_std_ha_3300_3_0.png":{"frame":{"x":1,"y":137,"w":21,"h":16},"rotated":false,"trimmed":false,"spriteSourceSize":{"x":0,"y":0,"w":21,"h":16},"sourceSize":{"w":21,"h":16}},"hat_U_sparkleparty2_h_std_ha_3300_7_0.png":{"frame":{"x":1,"y":155,"w":21,"h":16},"rotated":false,"trimmed":false,"spriteSourceSize":{"x":0,"y":0,"w":21,"h":16},"sourceSize":{"w":21,"h":16}}},"animations":{},"meta":{"app":"https://www.codeandweb.com/texturepacker","version":"1.0","image":"hat_U_sparkleparty2.png","format":"RGBA4444","size":{"w":23,"h":172},"scale":"1","smartupdate":"$TexturePacker:SmartUpdate:d2f4c6a08c00aaf69451aee03751b074:0794c32b38ae91b0b5edcbad322e2e7a:2b38c4155d4de5b55e0de0446cd4dfd5$","offset":{"h_std_ha_3300_7_0":[-22,83],"h_std_ha_3300_3_0":[-22,84],"h_std_ha_3300_2_0":[-21,84],"h_std_ha_3300_1_0":[-21,83],"h_std_ha_3300_0_0":[-22,83],"h_spk_ha_3300_7_0":[-22,84],"h_spk_ha_3300_3_0":[-22,85],"h_spk_ha_3300_2_0":[-21,85],"h_spk_ha_3300_1_0":[-21,84],"h_spk_ha_3300_0_0":[-22,84],"h_lay_ha_3300_2_0":[26,44],"h_lsp_ha_3300_2_0":[-37,-115]}}}