{"manifest":{"name":"divider_arm1","version":"0.1","assets":{"index":{},"divider_arm1_visualization":{},"divider_arm1_assets":{},"divider_arm1_logic":{},"divider_arm1_64_a_0_0":{},"divider_arm1_icon_a":{},"divider_arm1_32_a_0_0":{}},"aliases":{}},"spritesheet":{"frames":{"divider_arm1_divider_arm1_32_a_0_0.png":{"frame":{"x":1,"y":75,"w":31,"h":36},"rotated":false,"trimmed":false,"spriteSourceSize":{"x":0,"y":0,"w":31,"h":36},"sourceSize":{"w":31,"h":36}},"divider_arm1_divider_arm1_64_a_0_0.png":{"frame":{"x":1,"y":1,"w":58,"h":72},"rotated":false,"trimmed":false,"spriteSourceSize":{"x":0,"y":0,"w":58,"h":72},"sourceSize":{"w":58,"h":72}},"divider_arm1_divider_arm1_icon_a.png":{"frame":{"x":34,"y":75,"w":25,"h":30},"rotated":false,"trimmed":false,"spriteSourceSize":{"x":0,"y":0,"w":25,"h":30},"sourceSize":{"w":25,"h":30}}},"animations":{},"meta":{"app":"https://www.codeandweb.com/texturepacker","version":"1.0","image":"divider_arm1.png","format":"RGBA8888","size":{"w":60,"h":112},"scale":"1","smartupdate":"$TexturePacker:SmartUpdate:782eda917f38fb530b506253d6aeaa6c:184e5d127f716ead2fd8b779f82f6aae:93629d2d28cf00046d2410469a928a7f$"}},"animations":{}}