{"manifest":{"name":"party_block2","version":"0.1","assets":{"index":{},"party_block2_visualization":{},"party_block2_assets":{},"party_block2_logic":{},"party_block2_64_a_0_0":{},"party_block2_64_b_0_0":{},"party_block2_64_c_0_0":{},"party_block2_64_sd_0_0":{},"party_block2_icon_a":{},"party_block2_32_a_0_0":{},"party_block2_32_b_0_0":{},"party_block2_32_c_0_0":{}},"aliases":{}},"spritesheet":{"frames":{"party_block2_party_block2_32_a_0_0.png":{"frame":{"x":133,"y":36,"w":38,"h":20},"rotated":false,"trimmed":false,"spriteSourceSize":{"x":0,"y":0,"w":38,"h":20},"sourceSize":{"w":38,"h":20}},"party_block2_party_block2_32_b_0_0.png":{"frame":{"x":365,"y":1,"w":66,"h":29},"rotated":false,"trimmed":false,"spriteSourceSize":{"x":0,"y":0,"w":66,"h":29},"sourceSize":{"w":66,"h":29}},"party_block2_party_block2_32_c_0_0.png":{"frame":{"x":365,"y":32,"w":30,"h":28},"rotated":true,"trimmed":false,"spriteSourceSize":{"x":0,"y":0,"w":30,"h":28},"sourceSize":{"w":30,"h":28}},"party_block2_party_block2_64_a_0_0.png":{"frame":{"x":331,"y":1,"w":62,"h":32},"rotated":true,"trimmed":false,"spriteSourceSize":{"x":0,"y":0,"w":62,"h":32},"sourceSize":{"w":62,"h":32}},"party_block2_party_block2_64_b_0_0.png":{"frame":{"x":1,"y":1,"w":130,"h":56},"rotated":false,"trimmed":false,"spriteSourceSize":{"x":0,"y":0,"w":130,"h":56},"sourceSize":{"w":130,"h":56}},"party_block2_party_block2_64_c_0_0.png":{"frame":{"x":263,"y":1,"w":66,"h":57},"rotated":false,"trimmed":false,"spriteSourceSize":{"x":0,"y":0,"w":66,"h":57},"sourceSize":{"w":66,"h":57}},"party_block2_party_block2_64_sd_0_0.png":{"frame":{"x":133,"y":1,"w":128,"h":33},"rotated":false,"trimmed":false,"spriteSourceSize":{"x":0,"y":0,"w":128,"h":33},"sourceSize":{"w":128,"h":33}},"party_block2_party_block2_icon_a.png":{"frame":{"x":173,"y":36,"w":32,"h":23},"rotated":false,"trimmed":false,"spriteSourceSize":{"x":0,"y":0,"w":32,"h":23},"sourceSize":{"w":32,"h":23}}},"animations":{},"meta":{"app":"https://www.codeandweb.com/texturepacker","version":"1.0","image":"party_block2.png","format":"RGBA8888","size":{"w":432,"h":64},"scale":"1","smartupdate":"$TexturePacker:SmartUpdate:5b2f77ad8925e01fbb75bc9d9831c4c4:6e1c521c011893383ed00f0ec6f5f53f:3a1375ac286b64520f99b8b2b2e51ac7$"}},"animations":{}}