{"frames":{"acc_waist_U_cumberband_h_lay_wa_2864_2_0.png":{"frame":{"x":1,"y":47,"w":22,"h":21},"rotated":false,"trimmed":false,"spriteSourceSize":{"x":0,"y":0,"w":22,"h":21},"sourceSize":{"w":22,"h":21}},"acc_waist_U_cumberband_h_std_wa_2864_0_0.png":{"frame":{"x":1,"y":18,"w":25,"h":15},"rotated":false,"trimmed":false,"spriteSourceSize":{"x":0,"y":0,"w":25,"h":15},"sourceSize":{"w":25,"h":15}},"acc_waist_U_cumberband_h_std_wa_2864_1_0.png":{"frame":{"x":1,"y":70,"w":18,"h":10},"rotated":false,"trimmed":false,"spriteSourceSize":{"x":0,"y":0,"w":18,"h":10},"sourceSize":{"w":18,"h":10}},"acc_waist_U_cumberband_h_std_wa_2864_2_0.png":{"frame":{"x":1,"y":1,"w":26,"h":15},"rotated":false,"trimmed":false,"spriteSourceSize":{"x":0,"y":0,"w":26,"h":15},"sourceSize":{"w":26,"h":15}},"acc_waist_U_cumberband_h_std_wa_2864_7_0.png":{"frame":{"x":1,"y":35,"w":23,"h":10},"rotated":false,"trimmed":false,"spriteSourceSize":{"x":0,"y":0,"w":23,"h":10},"sourceSize":{"w":23,"h":10}}},"animations":{},"meta":{"app":"https://www.codeandweb.com/texturepacker","version":"1.0","image":"acc_waist_U_cumberband.png","format":"RGBA4444","size":{"w":28,"h":81},"scale":"1","smartupdate":"$TexturePacker:SmartUpdate:4f5aaf94f2398ea9aaff9ea606c9d5a3:aafcabbad555b4137a04764d3d25ae7a:8ad0954233af52cebfee562b11f5d5eb$","offset":{"h_std_wa_2864_2_0":[-20,29],"h_std_wa_2864_1_0":[-23,26],"h_std_wa_2864_3_0":[-22,26],"h_std_wa_2864_7_0":[-22,24],"h_std_wa_2864_0_0":[-19,28],"h_lay_wa_2864_2_0":[-15,16]}}}