{"manifest":{"name":"habboween_grass","version":"0.1","assets":{"index":{},"habboween_grass_visualization":{},"habboween_grass_assets":{},"habboween_grass_logic":{},"habboween_grass_64_a_0_0":{},"habboween_grass_64_b_0_0":{},"habboween_grass_64_c_0_0":{},"habboween_grass_64_d_0_0":{},"habboween_grass_64_e_0_0":{},"habboween_grass_64_e_2_0":{},"habboween_grass_64_e_4_0":{},"habboween_grass_64_e_6_0":{},"habboween_grass_64_f_0_0":{},"habboween_grass_64_f_2_0":{},"habboween_grass_64_f_4_0":{},"habboween_grass_64_f_6_0":{},"habboween_grass_64_g_0_0":{},"habboween_grass_64_sd_0_0":{},"habboween_grass_icon_a":{},"habboween_grass_32_a_0_0":{},"habboween_grass_32_b_0_0":{},"habboween_grass_32_c_0_0":{},"habboween_grass_32_d_0_0":{},"habboween_grass_32_e_0_0":{},"habboween_grass_32_e_2_0":{},"habboween_grass_32_e_4_0":{},"habboween_grass_32_e_6_0":{},"habboween_grass_32_f_0_0":{},"habboween_grass_32_f_2_0":{},"habboween_grass_32_f_4_0":{},"habboween_grass_32_f_6_0":{},"habboween_grass_32_g_0_0":{},"habboween_grass_32_sd_0_0":{}},"aliases":{}},"spritesheet":{"frames":{"habboween_grass_habboween_grass_32_a_0_0.png":{"frame":{"x":96,"y":77,"w":29,"h":20},"rotated":false,"trimmed":false,"spriteSourceSize":{"x":0,"y":0,"w":29,"h":20},"sourceSize":{"w":29,"h":20}},"habboween_grass_habboween_grass_32_b_0_0.png":{"frame":{"x":99,"y":202,"w":21,"h":28},"rotated":false,"trimmed":false,"spriteSourceSize":{"x":0,"y":0,"w":21,"h":28},"sourceSize":{"w":21,"h":28}},"habboween_grass_habboween_grass_32_c_0_0.png":{"frame":{"x":100,"y":99,"w":24,"h":26},"rotated":false,"trimmed":false,"spriteSourceSize":{"x":0,"y":0,"w":24,"h":26},"sourceSize":{"w":24,"h":26}},"habboween_grass_habboween_grass_32_d_0_0.png":{"frame":{"x":99,"y":168,"w":32,"h":26},"rotated":true,"trimmed":false,"spriteSourceSize":{"x":0,"y":0,"w":32,"h":26},"sourceSize":{"w":32,"h":26}},"habboween_grass_habboween_grass_32_e_0_0.png":{"frame":{"x":77,"y":181,"w":1,"h":1},"rotated":false,"trimmed":false,"spriteSourceSize":{"x":0,"y":0,"w":1,"h":1},"sourceSize":{"w":1,"h":1}},"habboween_grass_habboween_grass_32_e_2_0.png":{"frame":{"x":112,"y":165,"w":1,"h":1},"rotated":false,"trimmed":false,"spriteSourceSize":{"x":0,"y":0,"w":1,"h":1},"sourceSize":{"w":1,"h":1}},"habboween_grass_habboween_grass_32_e_4_0.png":{"frame":{"x":80,"y":181,"w":50,"h":17},"rotated":true,"trimmed":false,"spriteSourceSize":{"x":0,"y":0,"w":50,"h":17},"sourceSize":{"w":50,"h":17}},"habboween_grass_habboween_grass_32_e_6_0.png":{"frame":{"x":98,"y":129,"w":37,"h":12},"rotated":true,"trimmed":false,"spriteSourceSize":{"x":0,"y":0,"w":37,"h":12},"sourceSize":{"w":37,"h":12}},"habboween_grass_habboween_grass_32_f_4_0.png":{"frame":{"x":18,"y":238,"w":25,"h":10},"rotated":false,"trimmed":false,"spriteSourceSize":{"x":0,"y":0,"w":25,"h":10},"sourceSize":{"w":25,"h":10}},"habboween_grass_habboween_grass_32_f_6_0.png":{"frame":{"x":45,"y":238,"w":6,"h":6},"rotated":false,"trimmed":false,"spriteSourceSize":{"x":0,"y":0,"w":6,"h":6},"sourceSize":{"w":6,"h":6}},"habboween_grass_habboween_grass_32_g_0_0.png":{"frame":{"x":1,"y":235,"w":18,"h":15},"rotated":true,"trimmed":false,"spriteSourceSize":{"x":0,"y":0,"w":18,"h":15},"sourceSize":{"w":18,"h":15}},"habboween_grass_habboween_grass_32_sd_0_0.png":{"frame":{"x":35,"y":110,"w":63,"h":17},"rotated":false,"trimmed":false,"spriteSourceSize":{"x":0,"y":0,"w":63,"h":17},"sourceSize":{"w":63,"h":17}},"habboween_grass_habboween_grass_64_a_0_0.png":{"frame":{"x":31,"y":190,"w":47,"h":46},"rotated":false,"trimmed":false,"spriteSourceSize":{"x":0,"y":0,"w":47,"h":46},"sourceSize":{"w":47,"h":46}},"habboween_grass_habboween_grass_64_b_0_0.png":{"frame":{"x":35,"y":1,"w":63,"h":51},"rotated":false,"trimmed":false,"spriteSourceSize":{"x":0,"y":0,"w":63,"h":51},"sourceSize":{"w":63,"h":51}},"habboween_grass_habboween_grass_64_c_0_0.png":{"frame":{"x":35,"y":54,"w":59,"h":54},"rotated":false,"trimmed":false,"spriteSourceSize":{"x":0,"y":0,"w":59,"h":54},"sourceSize":{"w":59,"h":54}},"habboween_grass_habboween_grass_64_d_0_0.png":{"frame":{"x":31,"y":131,"w":57,"h":44},"rotated":true,"trimmed":false,"spriteSourceSize":{"x":0,"y":0,"w":57,"h":44},"sourceSize":{"w":57,"h":44}},"habboween_grass_habboween_grass_64_e_4_0.png":{"frame":{"x":1,"y":131,"w":102,"h":28},"rotated":true,"trimmed":false,"spriteSourceSize":{"x":0,"y":0,"w":102,"h":28},"sourceSize":{"w":102,"h":28}},"habboween_grass_habboween_grass_64_e_6_0.png":{"frame":{"x":100,"y":1,"w":74,"h":25},"rotated":true,"trimmed":false,"spriteSourceSize":{"x":0,"y":0,"w":74,"h":25},"sourceSize":{"w":74,"h":25}},"habboween_grass_habboween_grass_64_f_0_0.png":{"frame":{"x":18,"y":235,"w":1,"h":1},"rotated":false,"trimmed":false,"spriteSourceSize":{"x":0,"y":0,"w":1,"h":1},"sourceSize":{"w":1,"h":1}},"habboween_grass_habboween_grass_64_f_2_0.png":{"frame":{"x":77,"y":184,"w":1,"h":1},"rotated":false,"trimmed":false,"spriteSourceSize":{"x":0,"y":0,"w":1,"h":1},"sourceSize":{"w":1,"h":1}},"habboween_grass_habboween_grass_64_f_4_0.png":{"frame":{"x":77,"y":129,"w":50,"h":19},"rotated":true,"trimmed":false,"spriteSourceSize":{"x":0,"y":0,"w":50,"h":19},"sourceSize":{"w":50,"h":19}},"habboween_grass_habboween_grass_64_f_6_0.png":{"frame":{"x":112,"y":150,"w":13,"h":13},"rotated":false,"trimmed":false,"spriteSourceSize":{"x":0,"y":0,"w":13,"h":13},"sourceSize":{"w":13,"h":13}},"habboween_grass_habboween_grass_64_g_0_0.png":{"frame":{"x":112,"y":127,"w":13,"h":21},"rotated":false,"trimmed":false,"spriteSourceSize":{"x":0,"y":0,"w":13,"h":21},"sourceSize":{"w":13,"h":21}},"habboween_grass_habboween_grass_64_sd_0_0.png":{"frame":{"x":1,"y":1,"w":128,"h":32},"rotated":true,"trimmed":false,"spriteSourceSize":{"x":0,"y":0,"w":128,"h":32},"sourceSize":{"w":128,"h":32}},"habboween_grass_habboween_grass_icon_a.png":{"frame":{"x":80,"y":233,"w":30,"h":19},"rotated":false,"trimmed":false,"spriteSourceSize":{"x":0,"y":0,"w":30,"h":19},"sourceSize":{"w":30,"h":19}}},"animations":{},"meta":{"app":"https://www.codeandweb.com/texturepacker","version":"1.0","image":"habboween_grass.png","format":"RGBA8888","size":{"w":126,"h":254},"scale":"1","smartupdate":"$TexturePacker:SmartUpdate:482ea677ab2f4b813d9408f17d5eb00e:dad5936b49021f740b61b35d8a9b9e0b:84a7bdb95762ebcc65ff02ba1335f2b3$"}},"animations":{}}