{"manifest":{"name":"hween_c18_washpowder","version":"0.1","assets":{"index":{},"hween_c18_washpowder_visualization":{},"hween_c18_washpowder_assets":{},"hween_c18_washpowder_logic":{},"hween_c18_washpowder_64_sd_0_0":{},"hween_c18_washpowder_64_a_0_0":{},"hween_c18_washpowder_icon_a":{}},"aliases":{}},"spritesheet":{"frames":{"hween_c18_washpowder_hween_c18_washpowder_64_a_0_0.png":{"frame":{"x":1,"y":1,"w":40,"h":56},"rotated":true,"trimmed":false,"spriteSourceSize":{"x":0,"y":0,"w":40,"h":56},"sourceSize":{"w":40,"h":56}},"hween_c18_washpowder_hween_c18_washpowder_64_sd_0_0.png":{"frame":{"x":1,"y":43,"w":37,"h":18},"rotated":false,"trimmed":false,"spriteSourceSize":{"x":0,"y":0,"w":37,"h":18},"sourceSize":{"w":37,"h":18}},"hween_c18_washpowder_hween_c18_washpowder_icon_a.png":{"frame":{"x":40,"y":43,"w":20,"h":28},"rotated":false,"trimmed":false,"spriteSourceSize":{"x":0,"y":0,"w":20,"h":28},"sourceSize":{"w":20,"h":28}}},"animations":{},"meta":{"app":"https://www.codeandweb.com/texturepacker","version":"1.0","image":"hween_c18_washpowder.png","format":"RGBA8888","size":{"w":61,"h":72},"scale":"1","smartupdate":"$TexturePacker:SmartUpdate:844646b888508882cf1fe97e3935aa00:efdfa77b43baa99431dd577bf28dc4b6:6369c0ab8363dedd43a1dd9ae26a01b1$"}},"animations":{}}