{"manifest":{"name":"hat_U_earthhelm","version":"0.1","assets":{"h_lay_ha_2789_2_0":{"offset":"30,48"},"h_lsp_ha_2789_2_0":{"offset":"-34,-112"},"h_std_ha_2789_7_0":{"offset":"-14,83"},"h_std_ha_2789_3_0":{"offset":"-15,87"},"h_std_ha_2789_2_0":{"offset":"-12,88"},"h_std_ha_2789_1_0":{"offset":"-6,89"},"h_std_ha_2789_0_0":{"offset":"-10,87"},"h_spk_ha_2789_7_0":{"offset":"-14,83"},"h_spk_ha_2789_3_0":{"offset":"-15,87"},"h_spk_ha_2789_2_0":{"offset":"-12,88"},"h_spk_ha_2789_1_0":{"offset":"-6,89"},"h_spk_ha_2789_0_0":{"offset":"-10,87"}},"aliases":{}},"spritesheet":{"frames":{"hat_U_earthhelm_h_lay_ha_2789_2_0.png":{"frame":{"x":354,"y":1,"w":43,"h":39},"rotated":true,"trimmed":false,"spriteSourceSize":{"x":0,"y":0,"w":43,"h":39},"sourceSize":{"w":43,"h":39}},"hat_U_earthhelm_h_lsp_ha_2789_2_0.png":{"frame":{"x":313,"y":1,"w":44,"h":39},"rotated":true,"trimmed":false,"spriteSourceSize":{"x":0,"y":0,"w":44,"h":39},"sourceSize":{"w":44,"h":39}},"hat_U_earthhelm_h_spk_ha_2789_0_0.png":{"frame":{"x":119,"y":1,"w":36,"h":46},"rotated":false,"trimmed":false,"spriteSourceSize":{"x":0,"y":0,"w":36,"h":46},"sourceSize":{"w":36,"h":46}},"hat_U_earthhelm_h_spk_ha_2789_1_0.png":{"frame":{"x":76,"y":1,"w":41,"h":46},"rotated":false,"trimmed":false,"spriteSourceSize":{"x":0,"y":0,"w":41,"h":46},"sourceSize":{"w":41,"h":46}},"hat_U_earthhelm_h_spk_ha_2789_2_0.png":{"frame":{"x":39,"y":1,"w":35,"h":47},"rotated":false,"trimmed":false,"spriteSourceSize":{"x":0,"y":0,"w":35,"h":47},"sourceSize":{"w":35,"h":47}},"hat_U_earthhelm_h_spk_ha_2789_3_0.png":{"frame":{"x":1,"y":1,"w":36,"h":47},"rotated":false,"trimmed":false,"spriteSourceSize":{"x":0,"y":0,"w":36,"h":47},"sourceSize":{"w":36,"h":47}},"hat_U_earthhelm_h_std_ha_2789_0_0.png":{"frame":{"x":157,"y":1,"w":36,"h":46},"rotated":false,"trimmed":false,"spriteSourceSize":{"x":0,"y":0,"w":36,"h":46},"sourceSize":{"w":36,"h":46}},"hat_U_earthhelm_h_std_ha_2789_1_0.png":{"frame":{"x":270,"y":1,"w":41,"h":45},"rotated":false,"trimmed":false,"spriteSourceSize":{"x":0,"y":0,"w":41,"h":45},"sourceSize":{"w":41,"h":45}},"hat_U_earthhelm_h_std_ha_2789_2_0.png":{"frame":{"x":233,"y":1,"w":35,"h":46},"rotated":false,"trimmed":false,"spriteSourceSize":{"x":0,"y":0,"w":35,"h":46},"sourceSize":{"w":35,"h":46}},"hat_U_earthhelm_h_std_ha_2789_3_0.png":{"frame":{"x":195,"y":1,"w":36,"h":46},"rotated":false,"trimmed":false,"spriteSourceSize":{"x":0,"y":0,"w":36,"h":46},"sourceSize":{"w":36,"h":46}},"hat_U_earthhelm_h_std_ha_2789_7_0.png":{"frame":{"x":395,"y":1,"w":37,"h":41},"rotated":false,"trimmed":false,"spriteSourceSize":{"x":0,"y":0,"w":37,"h":41},"sourceSize":{"w":37,"h":41}}},"animations":{},"meta":{"app":"https://www.codeandweb.com/texturepacker","version":"1.0","image":"hat_U_earthhelm.png","format":"RGBA8888","size":{"w":433,"h":49},"scale":"1","smartupdate":"$TexturePacker:SmartUpdate:564a32c19cea0d4d5ab694ff0b5ae5cd:ccd760cb93cb30a07897fdb270d3819f:27fe0603f94fb7070e52758bc037fd18$"}},"animations":{}}