{"frames":{"Hoverplank_h_std_fx191_1_1_0_0.png":{"frame":{"x":1,"y":1,"w":30,"h":26},"rotated":true,"trimmed":false,"spriteSourceSize":{"x":0,"y":0,"w":30,"h":26},"sourceSize":{"w":30,"h":26}},"Hoverplank_h_std_fx191_1_1_1_0.png":{"frame":{"x":29,"y":40,"w":16,"h":23},"rotated":false,"trimmed":false,"spriteSourceSize":{"x":0,"y":0,"w":16,"h":23},"sourceSize":{"w":16,"h":23}},"Hoverplank_h_std_fx191_1_1_2_0.png":{"frame":{"x":1,"y":33,"w":30,"h":26},"rotated":true,"trimmed":false,"spriteSourceSize":{"x":0,"y":0,"w":30,"h":26},"sourceSize":{"w":30,"h":26}},"Hoverplank_h_std_fx191_1_1_3_0.png":{"frame":{"x":29,"y":1,"w":37,"h":19},"rotated":true,"trimmed":false,"spriteSourceSize":{"x":0,"y":0,"w":37,"h":19},"sourceSize":{"w":37,"h":19}},"Hoverplank_h_std_fx191_2_1_0_0.png":{"frame":{"x":47,"y":40,"w":16,"h":18},"rotated":false,"trimmed":false,"spriteSourceSize":{"x":0,"y":0,"w":16,"h":18},"sourceSize":{"w":16,"h":18}},"Hoverplank_h_std_fx191_2_1_1_0.png":{"frame":{"x":50,"y":21,"w":16,"h":17},"rotated":false,"trimmed":false,"spriteSourceSize":{"x":0,"y":0,"w":16,"h":17},"sourceSize":{"w":16,"h":17}},"Hoverplank_h_std_fx191_2_1_2_0.png":{"frame":{"x":50,"y":1,"w":16,"h":18},"rotated":false,"trimmed":false,"spriteSourceSize":{"x":0,"y":0,"w":16,"h":18},"sourceSize":{"w":16,"h":18}},"Hoverplank_h_std_fx191_2_1_3_0.png":{"frame":{"x":47,"y":60,"w":1,"h":1},"rotated":false,"trimmed":false,"spriteSourceSize":{"x":0,"y":0,"w":1,"h":1},"sourceSize":{"w":1,"h":1}}},"animations":{},"meta":{"app":"https://www.codeandweb.com/texturepacker","version":"1.0","image":"Hoverplank.png","format":"RGBA4444","size":{"w":67,"h":64},"scale":"1","smartupdate":"$TexturePacker:SmartUpdate:e414d797c4ff08edf86444396323db51:ae5bd9530fe644292e021669117a812a:87bfa519283df3def99cbabb1a9d4825$","offset":{"h_std_fx191_1_1_2_0":[-24,20],"h_std_fx191_2_1_2_0":[-14,8],"h_std_fx191_1_1_1_0":[-26,24],"h_std_fx191_2_1_1_0":[-26,6],"h_std_fx191_1_1_0_0":[-12,21],"h_std_fx191_2_1_0_0":[-36,9],"h_std_fx191_1_1_3_0":[-15,14],"h_std_fx191_2_1_3_0":[-49,-4],"h_std_fx191_1_1_7_0":[-15,14],"h_std_fx191_2_1_7_0":[-18,-4]}}}